huaweicloudsdkdli/__init__.py
huaweicloudsdkdli/v1/__init__.py
huaweicloudsdkdli/v1/dli_async_client.py
huaweicloudsdkdli/v1/dli_client.py
huaweicloudsdkdli/v1/model/__init__.py
huaweicloudsdkdli/v1/model/advanced_queue_property.py
huaweicloudsdkdli/v1/model/associate_queue_to_elastic_resource_pool_request.py
huaweicloudsdkdli/v1/model/associate_queue_to_elastic_resource_pool_request_body.py
huaweicloudsdkdli/v1/model/associate_queue_to_elastic_resource_pool_response.py
huaweicloudsdkdli/v1/model/associate_queue_to_enhanced_connection_request.py
huaweicloudsdkdli/v1/model/associate_queue_to_enhanced_connection_request_body.py
huaweicloudsdkdli/v1/model/associate_queue_to_enhanced_connection_response.py
huaweicloudsdkdli/v1/model/auth_info.py
huaweicloudsdkdli/v1/model/authorization_privilege.py
huaweicloudsdkdli/v1/model/available_queue_info.py
huaweicloudsdkdli/v1/model/batch_create_resource_tags_request.py
huaweicloudsdkdli/v1/model/batch_create_resource_tags_request_body.py
huaweicloudsdkdli/v1/model/batch_create_resource_tags_response.py
huaweicloudsdkdli/v1/model/batch_delete_flink_jobs_request.py
huaweicloudsdkdli/v1/model/batch_delete_flink_jobs_request_body.py
huaweicloudsdkdli/v1/model/batch_delete_flink_jobs_response.py
huaweicloudsdkdli/v1/model/batch_delete_queue_plans_request.py
huaweicloudsdkdli/v1/model/batch_delete_queue_plans_request_body.py
huaweicloudsdkdli/v1/model/batch_delete_queue_plans_response.py
huaweicloudsdkdli/v1/model/batch_delete_resource_tags_request.py
huaweicloudsdkdli/v1/model/batch_delete_resource_tags_request_body.py
huaweicloudsdkdli/v1/model/batch_delete_resource_tags_response.py
huaweicloudsdkdli/v1/model/batch_delete_sql_job_templates_request.py
huaweicloudsdkdli/v1/model/batch_delete_sql_job_templates_request_body.py
huaweicloudsdkdli/v1/model/batch_delete_sql_job_templates_response.py
huaweicloudsdkdli/v1/model/batch_run_flink_jobs_request.py
huaweicloudsdkdli/v1/model/batch_run_flink_jobs_request_body.py
huaweicloudsdkdli-3.1.184.dist-info/METADATA
huaweicloudsdkdli-3.1.184.dist-info/WHEEL
huaweicloudsdkdli-3.1.184.dist-info/licenses/LICENSE
huaweicloudsdkdli-3.1.184.dist-info/RECORD
